qwen_tokenizer-0.2.0.dist-info/METADATA
qwen_tokenizer-0.2.0.dist-info/WHEEL
qwen_tokenizer-0.2.0.dist-info/entry_points.txt
qwen_tokenizer/__init__.py
qwen_tokenizer/qwen_tokenizer.py
qwen_tokenizer/resources/qwen.tiktoken
qwen_tokenizer/tokenizer.py
qwen_tokenizer/tokenizer_base.py
qwen_tokenizer-0.2.0.dist-info/RECORD
