Metadata-Version: 2.1
Name: qwen-tokenizer
Version: 0.2.0
Summary: Lightweight tokenizer for qwen.
Author-Email: Anderson <andersonby@163.com>
License: MIT
Requires-Python: >=3.8
Requires-Dist: tiktoken>=0.7.0
